{
	"elements": [
		{
			"from": [7, 0, 7],
			"to": [9, 3, 8],
			"rotation": {"angle": 0, "axis": "y", "origin": [6.5, 0, 7]},
			"faces": {
				"north": {"uv": [3, 13, 5, 16], "texture": "#Layer0"},
				"east": {"uv": [8, 13, 9, 16], "texture": "#Layer0"},
				"south": {"uv": [5, 13, 7, 16], "texture": "#Layer0"},
				"west": {"uv": [7, 13, 8, 16], "texture": "#Layer0"},
				"down": {"uv": [3, 11, 5, 12], "texture": "#Layer0"}
			}
		},
		{
			"from": [6, 3, 6],
			"to": [10, 11, 9],
			"rotation": {"angle": 0, "axis": "y", "origin": [6, 3, 6]},
			"faces": {
				"north": {"uv": [0, 0, 4, 8], "texture": "#Layer0"},
				"east": {"uv": [0, 8, 3, 16], "texture": "#Layer0"},
				"south": {"uv": [4, 0, 8, 8], "texture": "#Layer0"},
				"west": {"uv": [8, 0, 11, 8], "texture": "#Layer0"},
				"up": {"uv": [7, 11, 3, 8], "texture": "#Layer0"},
				"down": {"uv": [11, 8, 7, 11], "texture": "#Layer0"}
			}
		}
	],
	"display": {
		"thirdperson_righthand": {
			"translation": [0, 3.25, 1.25],
			"scale": [0.5, 0.5, 0.5]
		},
		"thirdperson_lefthand": {
			"translation": [0, 3.25, 1.25],
			"scale": [0.5, 0.5, 0.5]
		},
		"firstperson_righthand": {
			"rotation": [0, -65, 0],
			"translation": [0, 6.75, 0]
		},
		"firstperson_lefthand": {
			"rotation": [0, -65, 0],
			"translation": [0, 6.75, 0]
		},
		"ground": {
			"translation": [0, 3.1, 0],
			"scale": [0.6, 0.6, 0.6]
		},
		"gui": {
			"rotation": [27, 23, -22],
			"translation": [0, 1.25, 0],
			"scale": [1.1, 1.1, 1.1]
		},
		"head": {
			"translation": [0, 13.5, 0]
		}
	}
}