{
  "display": {
    "icon": {
      "count": 1,
      "id": "smasher:qiaolezi_matcha"
    },
    "title": {
      "text": "抹茶巧乐兹"
    },
    "description": {
      "text": "这东西不应该存在"
    },
    "frame": "task",
    "show_toast": true,
    "announce_to_chat": true,
    "hidden": false
  },
  "parent": "minecraft:story/root",
  "criteria": {
    "has_eaten": {
      "trigger": "minecraft:consume_item",
      "conditions": {
        "item": {
          "items": [
            "smasher:qiaolezi_matcha"
          ]
        }
      }
    }
  },
  "requirements": [
    [
      "has_eaten"
    ]
  ]
}
